AUTHORS.rst
CONTRIBUTING.rst
HISTORY.rst
LICENSE
MANIFEST.in
README.rst
setup.cfg
setup.py
asyncpg_simpleorm/__init__.py
asyncpg_simpleorm/abstract.py
asyncpg_simpleorm/async_model.py
asyncpg_simpleorm/connection_managers.py
asyncpg_simpleorm/exceptions.py
asyncpg_simpleorm.egg-info/PKG-INFO
asyncpg_simpleorm.egg-info/SOURCES.txt
asyncpg_simpleorm.egg-info/dependency_links.txt
asyncpg_simpleorm.egg-info/not-zip-safe
asyncpg_simpleorm.egg-info/requires.txt
asyncpg_simpleorm.egg-info/top_level.txt
asyncpg_simpleorm/statements/__init__.py
asyncpg_simpleorm/statements/abstract.py
asyncpg_simpleorm/statements/base_statement.py
docs/Makefile
docs/asyncpg_simpleorm.rst
docs/asyncpg_simpleorm.statements.rst
docs/authors.rst
docs/conf.py
docs/contributing.rst
docs/history.rst
docs/index.rst
docs/installation.rst
docs/make.bat
docs/modules.rst
docs/readme.rst
docs/usage.rst
examples/__init__.py
examples/db.py
examples/user.py
tests/__init__.py
tests/conftest.py
tests/test_asyncpg_simpleorm.py
tests/test_model.py
tests/test_statements.py