Metadata-Version: 1.1
Name: asyncpg-simpleorm
Version: 0.1.2
Summary: Simple orm for asyncpg
Home-page: https://github.com/m-housh/asyncpg_simpleorm
Author: Michael Housh
Author-email: mhoush@houshhomeenergy.com
License: Apache Software License 2.0
Keywords: asyncpg_simpleorm
Platform: UNKNOWN
Classifier: Development Status :: 2 - Pre-Alpha
Classifier: Intended Audience :: Developers
Classifier: License :: OSI Approved :: Apache Software License
Classifier: Natural Language :: English
Classifier: Programming Language :: Python :: 3.6
